xhermes/__init__.py
xhermes/accessors.py
xhermes/load.py
xhermes/utils.py
xhermes-0.1.0.dist-info/METADATA
xhermes-0.1.0.dist-info/WHEEL
xhermes-0.1.0.dist-info/top_level.txt
xhermes-0.1.0.dist-info/RECORD
