Metadata-Version: 2.4
Name: xhermes
Version: 0.1.0
Summary: Analyse data from Hermes-3 simulations using xarray
License: Apache
Classifier: Development Status :: 2 - Pre-Alpha
Classifier: Intended Audience :: Science/Research
Classifier: Intended Audience :: Education
Classifier: Intended Audience :: Developers
Classifier: License :: OSI Approved :: Apache Software License
Classifier: Natural Language :: English
Classifier: Operating System :: POSIX :: Linux
Classifier: Programming Language :: Python :: 3.6
Classifier: Topic :: Scientific/Engineering :: Physics
Requires-Dist: xarray
Requires-Dist: xbout
Dynamic: classifier
Dynamic: description
Dynamic: description-content-type
Dynamic: license
Dynamic: requires-dist
Dynamic: summary
